README.md
pypi.py
therefore.egg-info/PKG-INFO
therefore.egg-info/SOURCES.txt
therefore.egg-info/dependency_links.txt
therefore.egg-info/top_level.txt