Metadata-Version: 1.2
Name: therefore
Version: 0.0.0a0
Summary: therefore
Home-page: https://github.com/mattian7741/therefore
Author: Matthew Hansen
Author-email: therefore@mattian.com
License: MIT
Download-URL: https://github.com/mattian7741/therefore/archive/v0.0.00-alpha.tar.gz
Platform: UNKNOWN
Classifier: Development Status :: 3 - Alpha
Classifier: Intended Audience :: Developers
Classifier: Topic :: Software Development :: Build Tools
Classifier: License :: OSI Approved :: MIT License
Classifier: Programming Language :: Python :: 3
Classifier: Programming Language :: Python :: 3.4
Classifier: Programming Language :: Python :: 3.5
Classifier: Programming Language :: Python :: 3.6
Requires-Python: >=3
